{"_id":{"$oid":"5d53a24bb333644f68907e4e"},"username":"jackson","password":"jackson","calendarItems":[{"calendarItemID":{"$oid":"5d5bc96e10a08a5640fe11e9"},"title":"Swimming lesson","startTime":"2019-09-05T17:30:00.000+00:00","endTime":"2019-09-05T18:30:00.000+00:00"},{"calendarItemID":{"$oid":"5d5bc99110a08a5640fe11ea"},"title":"Trip to Auckland","startTime":"2019-09-07T09:00:00.000+00:00","endTime":"2019-09-12T17:00:00.000+00:00"}],"scheduleItems":[{"scheduleItemID":{"$oid":"5d5bc9a310a08a5640fe11eb"},"title":"Work","category":{"$numberInt":"3"},"startTime":{"$numberInt":"540"},"endTime":{"$numberInt":"1020"}},{"scheduleItemID":{"$oid":"5d5bc9ae10a08a5640fe11ec"},"title":"Dinner","category":{"$numberInt":"0"},"startTime":{"$numberInt":"1020"},"endTime":{"$numberInt":"1080"}}],"tasks":[{"taskID":{"$oid":"5d5bc9cd10a08a5640fe11ed"},"title":"Laundry","priority":{"$numberInt":"3"},"estimatedTime":{"$numberInt":"30"},"startTime":"2019-09-05T18:30:00.000+00:00"},{"taskID":{"$oid":"5d5bc9e710a08a5640fe11ee"},"title":"Get gym membership","priority":{"$numberInt":"1"},"estimatedTime":{"$numberInt":"15"},"startTime":null}]}
{"_id":{"$oid":"5d53a24bb333644f68907e4f"},"username":"georgia","password":"georgia","calendarItems":[{"calendarItemID":{"$oid":"5d5bcbc510a08a5640fe11ef"},"title":"Tennis lesson","startTime":"2019-09-08T17:30:00.000+00:00","endTime":"2019-09-08T18:30:00.000+00:00"},{"calendarItemID":{"$oid":"5d5bcbd110a08a5640fe11f0"},"title":"Trip to Wellington","startTime":"2019-09-09T09:00:00.000+00:00","endTime":"2019-09-13T17:00:00.000+00:00"}],"scheduleItems":[{"scheduleItemID":{"$oid":"5d5bcbe410a08a5640fe11f1"},"title":"Work","category":{"$numberInt":"3"},"startTime":{"$numberInt":"600"},"endTime":{"$numberInt":"1080"}},{"scheduleItemID":{"$oid":"5d5bcbf110a08a5640fe11f2"},"title":"Dinner","category":{"$numberInt":"0"},"startTime":{"$numberInt":"1080"},"endTime":{"$numberInt":"1140"}}],"tasks":[{"taskID":{"$oid":"5d5bcc0a10a08a5640fe11f3"},"title":"Dishes","priority":{"$numberInt":"3"},"estimatedTime":{"$numberInt":"30"},"startTime":"2019-09-06T18:30:00.000+00:00"},{"taskID":{"$oid":"5d5bcc1310a08a5640fe11f4"},"title":"Get tennis membership","priority":{"$numberInt":"1"},"estimatedTime":{"$numberInt":"15"},"startTime":null}]}
